[
  {
    "name": "org_slug",
    "type": "STRING",
    "mode": "REQUIRED",
    "description": "Unique identifier for the organization"
  },
  {
    "name": "company_name",
    "type": "STRING",
    "mode": "REQUIRED",
    "description": "Company or organization name"
  },
  {
    "name": "admin_email",
    "type": "STRING",
    "mode": "REQUIRED",
    "description": "Primary administrator email address"
  },
  {
    "name": "org_dataset_id",
    "type": "STRING",
    "mode": "REQUIRED",
    "description": "BigQuery dataset ID for this organization's data"
  },
  {
    "name": "status",
    "type": "STRING",
    "mode": "REQUIRED",
    "description": "Organization status: ACTIVE, SUSPENDED, DELETED"
  },
  {
    "name": "subscription_plan",
    "type": "STRING",
    "mode": "NULLABLE",
    "description": "Current subscription plan tier"
  },
  {
    "name": "default_currency",
    "type": "STRING",
    "mode": "NULLABLE",
    "description": "ISO 4217 currency code (e.g., USD, EUR, AED). Default: USD"
  },
  {
    "name": "default_country",
    "type": "STRING",
    "mode": "NULLABLE",
    "description": "ISO 3166-1 alpha-2 country code (e.g., US, AE). Auto-inferred from currency"
  },
  {
    "name": "default_language",
    "type": "STRING",
    "mode": "NULLABLE",
    "description": "BCP 47 language tag (e.g., en, ar). Default: en"
  },
  {
    "name": "default_timezone",
    "type": "STRING",
    "mode": "NULLABLE",
    "description": "IANA timezone identifier (e.g., UTC, Asia/Dubai). Default: UTC"
  },
  {
    "name": "created_at",
    "type": "TIMESTAMP",
    "mode": "REQUIRED",
    "description": "Timestamp when organization was created"
  },
  {
    "name": "updated_at",
    "type": "TIMESTAMP",
    "mode": "NULLABLE",
    "description": "Timestamp of last update"
  }
]
